fais/TweetAnalyzer.py
fais/TweetCriteria.py
fais/TweetManager.py
fais/TweetModel.py
fais/TwitterClient.py
fais/USGSFloodCriteria.py
fais/USGSFloodManager.py
fais/__init__.py
fais/imageProcessor.py
fais/nasagatherer.py
fais/twittergatherer.py
fais/usgsgatherer.py
fais-0.0.18.dist-info/LICENSE
fais-0.0.18.dist-info/METADATA
fais-0.0.18.dist-info/WHEEL
fais-0.0.18.dist-info/top_level.txt
fais-0.0.18.dist-info/RECORD
