Metadata-Version: 2.1
Name: fais
Version: 0.0.18
Summary: USGS and Twitter data gathering and analysis tools
Home-page: https://github.com/VidyaSamadi/Research-Team-private
Author: Nattapon Donratanapat
Author-email: pleuk5667@gmail.com
License: UNKNOWN
Platform: UNKNOWN
Classifier: Programming Language :: Python :: 3
Classifier: License :: OSI Approved :: MIT License
Classifier: Operating System :: OS Independent
Requires-Dist: pandas
Requires-Dist: numpy
Requires-Dist: urllib3
Requires-Dist: requests
Requires-Dist: opencv-python
Requires-Dist: netCDF4
Requires-Dist: matplotlib
Requires-Dist: textblob
Requires-Dist: pyquery
Requires-Dist: tweepy
Requires-Dist: Pillow
